canoll/__init__.py
canoll/ops.py
canoll/tensor.py
canoll-1.0.0.dist-info/licenses/LICENSE
canoll-1.0.0.dist-info/METADATA
canoll-1.0.0.dist-info/WHEEL
canoll-1.0.0.dist-info/top_level.txt
canoll-1.0.0.dist-info/RECORD
