Metadata-Version: 2.4
Name: canoll
Version: 1.0.0
Summary: Library array ringan tanpa NumPy.
Author-email: xycan <eternals-tolong@gmail.com>
License: Eternals Vlazars License
License-File: LICENSE
Dynamic: license-file
